iqsopenapi/__init__.py
iqsopenapi/environment.py
iqsopenapi/basicdata/BasicDataApi.py
iqsopenapi/basicdata/IBasicDataApi.py
iqsopenapi/basicdata/__init__.py
iqsopenapi/core/IStrategyLoader.py
iqsopenapi/core/Scheduler.py
iqsopenapi/core/Strategy.py
iqsopenapi/core/StrategyContext.py
iqsopenapi/core/StrategyLoader.py
iqsopenapi/core/__init__.py
iqsopenapi/core/events.py
iqsopenapi/example/__init__.py
iqsopenapi/example/demo.py
iqsopenapi/example/run_code_demo.py
iqsopenapi/example/run_file_demo.py
iqsopenapi/example/run_func_demo.py
iqsopenapi/example/teststrategy.py
iqsopenapi/external/ExternalNotify.py
iqsopenapi/external/__init__.py
iqsopenapi/marketdata/IMarketApi.py
iqsopenapi/marketdata/MarketApi.py
iqsopenapi/marketdata/__init__.py
iqsopenapi/marketdata/message/HeartBeatReq.py
iqsopenapi/marketdata/message/IMessage.py
iqsopenapi/marketdata/message/ReplyResp.py
iqsopenapi/marketdata/message/SubscribeReq.py
iqsopenapi/marketdata/message/UnsubscribeReq.py
iqsopenapi/marketdata/message/__init__.py
iqsopenapi/models/Account.py
iqsopenapi/models/BarData.py
iqsopenapi/models/Contract.py
iqsopenapi/models/Order.py
iqsopenapi/models/Position.py
iqsopenapi/models/ResultInfo.py
iqsopenapi/models/TickData.py
iqsopenapi/models/Trade.py
iqsopenapi/models/__init__.py
iqsopenapi/trade/ITradeApi.py
iqsopenapi/trade/__init__.py
iqsopenapi/trade/papertrade/PaperTradeApi.py
iqsopenapi/trade/papertrade/YKPaperTradeApi.py
iqsopenapi/trade/papertrade/__init__.py
iqsopenapi/trade/papertrade/message/HeartBeatReq.py
iqsopenapi/trade/papertrade/message/IMessage.py
iqsopenapi/trade/papertrade/message/ReplyResp.py
iqsopenapi/trade/papertrade/message/__init__.py
iqsopenapi/trade/realtrade/Models.py
iqsopenapi/trade/realtrade/ParseManager.py
iqsopenapi/trade/realtrade/PushQuoteSubscriber.py
iqsopenapi/trade/realtrade/RealTradeApi.py
iqsopenapi/trade/realtrade/RealTradeApiCore.py
iqsopenapi/trade/realtrade/SupervisionHelper.py
iqsopenapi/trade/realtrade/TradeEnums.py
iqsopenapi-0.3.0.dist-info/LICENSE
iqsopenapi-0.3.0.dist-info/METADATA
iqsopenapi-0.3.0.dist-info/WHEEL
iqsopenapi-0.3.0.dist-info/top_level.txt
iqsopenapi-0.3.0.dist-info/RECORD
