Metadata-Version: 2.1
Name: iqsopenapi
Version: 0.3.0
Summary: inquantstudio quant open api
Home-page: http://www.inquantstudio.com/
Author: inquantstudio
Author-email: sunliusi@hotmail.com
License: UNKNOWN
Platform: UNKNOWN
Classifier: Programming Language :: Python
Classifier: Programming Language :: Python :: Implementation
Classifier: Programming Language :: Python :: 3
Classifier: Programming Language :: Python :: 3.4
Classifier: Programming Language :: Python :: 3.5
Classifier: Programming Language :: Python :: 3.6
Classifier: Programming Language :: Python :: 3.7
Classifier: License :: OSI Approved :: MIT License
Classifier: Operating System :: OS Independent
Requires-Dist: pycryptodome (>=3.7.2)
Requires-Dist: websocket-client (>=0.57.0)
